bfbrain/AL_Metrics.py
bfbrain/BFB_Learner.py
bfbrain/Custom_Layers.py
bfbrain/Data_Manager.py
bfbrain/False_Proximity_Test.py
bfbrain/Hypersphere_Formulas.py
bfbrain/Jax_Oracle.py
bfbrain/Potential_Functions.py
bfbrain/Score_Functions.py
bfbrain/__init__.py
bfbrain-1.1.dist-info/LICENSE
bfbrain-1.1.dist-info/METADATA
bfbrain-1.1.dist-info/WHEEL
bfbrain-1.1.dist-info/RECORD
